surfer/__init__.py
surfer/surf.py
google_surfer-0.0.4.dist-info/LICENSE
google_surfer-0.0.4.dist-info/METADATA
google_surfer-0.0.4.dist-info/WHEEL
google_surfer-0.0.4.dist-info/top_level.txt
google_surfer-0.0.4.dist-info/RECORD
