Metadata-Version: 2.1
Name: google-surfer
Version: 0.0.4
Summary: A package to search for URLs
Author-email: Thai Nguyen <thainm.uet@gmail.com>
Project-URL: Homepage, https://github.com/thai-nm/google-surfer
Project-URL: Bug Tracker, https://github.com/thai-nm/google-surfer/issues
Classifier: Programming Language :: Python :: 3
Classifier: License :: OSI Approved :: MIT License
Classifier: Operating System :: OS Independent
Requires-Python: >=3.9
License-File: LICENSE
